<?xml version="1.0" encoding="UTF-8"?>
<watchlist household="Hall family" curatedBy="Brian and Karen" updated="2026-01-31">
  <category name="Family Movie Night" night="Friday">
    <title name="The Wild Robot" rating="G" runtimeMin="102" status="watched" twinsApproved="true"/>
    <title name="Inside Out 2" rating="PG" runtimeMin="96" status="watched" twinsApproved="true"/>
    <title name="Moana" rating="PG" runtimeMin="107" status="rewatch favorite" twinsApproved="true"/>
    <title name="Paddington in Peru" rating="PG" runtimeMin="103" status="queued" twinsApproved="true"/>
  </category>
  <category name="Twins Pick" service="Disney Plus">
    <title name="Bluey" type="series" status="on rotation" note="Ethan and Lily both ask for this"/>
    <title name="Encanto" type="film" status="watched" note="Lily knows every song"/>
    <title name="Cars" type="film" status="queued" note="Ethan choice for the next soccer rain day"/>
  </category>
  <category name="Parents After Bedtime" service="Netflix">
    <title name="Formula 1 Drive to Survive" type="series" status="watching" note="weeknight wind down"/>
    <title name="A documentary on endurance athletes" type="film" status="queued"/>
  </category>
  <category name="Sports" service="YouTube TV">
    <title name="Premier League match replays" type="live and replay" status="weekly" note="Arsenal first, every match"/>
    <title name="Champions League nights" type="live" status="midweek"/>
  </category>
  <rules>
    <rule>Twins screen time stays limited on school nights</rule>
    <rule>Friday night film is a full family pick, chosen in rotation</rule>
    <rule>Saturday daytime stays open for soccer and the gym, not screens</rule>
  </rules>
</watchlist>
