[
  {
    "id": "price_HalfMarathon_Reg",
    "product": "prod_HalfMarathon",
    "unit_amount": 6500,
    "currency": "usd",
    "recurring_interval": "one_time",
    "active": "true",
    "nickname": "Columbus Half Marathon Standard Entry"
  },
  {
    "id": "price_10K_Reg",
    "product": "prod_10K",
    "unit_amount": 3975,
    "currency": "usd",
    "recurring_interval": "one_time",
    "active": "true",
    "nickname": "Scioto Mile 10K Entry"
  },
  {
    "id": "price_CEUWebinar_Single",
    "product": "prod_CEUWebinar",
    "unit_amount": 4500,
    "currency": "usd",
    "recurring_interval": "one_time",
    "active": "true",
    "nickname": "CEU Webinar Single Session"
  },
  {
    "id": "price_CEUOnline_Bundle",
    "product": "prod_CEUOnline",
    "unit_amount": 12900,
    "currency": "usd",
    "recurring_interval": "one_time",
    "active": "true",
    "nickname": "CEU Online 8-Hour Bundle"
  },
  {
    "id": "price_CEUOnline_Single",
    "product": "prod_CEUOnline",
    "unit_amount": 2900,
    "currency": "usd",
    "recurring_interval": "month",
    "active": "true",
    "nickname": "CEU Monthly Access"
  },
  {
    "id": "price_HalfMarathon_2025",
    "product": "prod_HalfMarathon",
    "unit_amount": 4500,
    "currency": "usd",
    "recurring_interval": "one_time",
    "active": "false",
    "nickname": "Columbus Half Marathon 2025 Entry (Archived)"
  },
  {
    "id": "price_HalfMarathon_Early",
    "product": "prod_HalfMarathon",
    "unit_amount": 5500,
    "currency": "usd",
    "recurring_interval": "one_time",
    "active": "true",
    "nickname": "Columbus Half Marathon Early Bird Entry"
  },
  {
    "id": "price_10K_Early",
    "product": "prod_10K",
    "unit_amount": 2975,
    "currency": "usd",
    "recurring_interval": "one_time",
    "active": "false",
    "nickname": "Scioto Mile 10K Early Bird (Archived)"
  },
  {
    "id": "price_10K_Group",
    "product": "prod_10K",
    "unit_amount": 3500,
    "currency": "usd",
    "recurring_interval": "one_time",
    "active": "true",
    "nickname": "Scioto Mile 10K Group Rate (4+)"
  },
  {
    "id": "price_CEUWebinar_Multi",
    "product": "prod_CEUWebinar",
    "unit_amount": 8000,
    "currency": "usd",
    "recurring_interval": "one_time",
    "active": "true",
    "nickname": "CEU Webinar 2-Pack Bundle"
  },
  {
    "id": "price_CEUOnline_Annual",
    "product": "prod_CEUOnline",
    "unit_amount": 29900,
    "currency": "usd",
    "recurring_interval": "year",
    "active": "true",
    "nickname": "CEU Annual Access Plan"
  },
  {
    "id": "price_HalfMarathon_Virtual",
    "product": "prod_HalfMarathon",
    "unit_amount": 3500,
    "currency": "usd",
    "recurring_interval": "one_time",
    "active": "false",
    "nickname": "Virtual Half Marathon (COVID Year - Archived)"
  },
  {
    "id": "price_10K_Virtual",
    "product": "prod_10K",
    "unit_amount": 1500,
    "currency": "usd",
    "recurring_interval": "one_time",
    "active": "false",
    "nickname": "Virtual 10K Entry (Archived)"
  },
  {
    "id": "price_CEUWebinar_Upgrade",
    "product": "prod_CEUWebinar",
    "unit_amount": 500,
    "currency": "usd",
    "recurring_interval": "one_time",
    "active": "true",
    "nickname": "CEU Webinar Certificate Upgrade"
  },
  {
    "id": "price_CEUOnline_Trial",
    "product": "prod_CEUOnline",
    "unit_amount": 0,
    "currency": "usd",
    "recurring_interval": "month",
    "active": "false",
    "nickname": "CEU 30-Day Trial (Discontinued)"
  },
  {
    "id": "price_HalfM_Charity",
    "product": "prod_HalfMarathon",
    "unit_amount": 7500,
    "currency": "usd",
    "recurring_interval": "one_time",
    "active": "true",
    "nickname": "Columbus Half Marathon Charity Bib Entry"
  },
  {
    "id": "price_10K_Charity",
    "product": "prod_10K",
    "unit_amount": 5000,
    "currency": "usd",
    "recurring_interval": "one_time",
    "active": "true",
    "nickname": "Scioto Mile 10K Charity Bib"
  },
  {
    "id": "price_CEUWebinar_CEU3",
    "product": "prod_CEUWebinar",
    "unit_amount": 12000,
    "currency": "usd",
    "recurring_interval": "one_time",
    "active": "true",
    "nickname": "CEU Webinar 3-Pack Clinic Bundle"
  },
  {
    "id": "price_HalfM_2024",
    "product": "prod_HalfMarathon",
    "unit_amount": 4500,
    "currency": "usd",
    "recurring_interval": "one_time",
    "active": "false",
    "nickname": "Columbus Half Marathon 2024 Registration (Archived)"
  },
  {
    "id": "price_Micro_CEU",
    "product": "prod_CEUWebinar",
    "unit_amount": 1500,
    "currency": "usd",
    "recurring_interval": "one_time",
    "active": "true",
    "nickname": "CEU Micro-Learning Single Session"
  },
  {
    "id": "price_Webflow_Guide",
    "product": "prod_Webflow_Guide",
    "unit_amount": 1600,
    "currency": "usd",
    "recurring_interval": "month",
    "active": "true",
    "nickname": "Webflow CMS Hosting - Guide Monthly"
  },
  {
    "id": "price_Klaviyo_Guide",
    "product": "prod_Klaviyo_Guide",
    "unit_amount": 2000,
    "currency": "usd",
    "recurring_interval": "month",
    "active": "true",
    "nickname": "Klaviyo Email - Guide Monthly"
  },
  {
    "id": "price_Contentful_Guide",
    "product": "prod_Contentful_Guide",
    "unit_amount": 900,
    "currency": "usd",
    "recurring_interval": "month",
    "active": "true",
    "nickname": "Contentful CMS - Guide Monthly"
  },
  {
    "id": "price_SendGrid_Guide",
    "product": "prod_SendGrid_Guide",
    "unit_amount": 1995,
    "currency": "usd",
    "recurring_interval": "month",
    "active": "true",
    "nickname": "SendGrid Email - Guide Monthly"
  },
  {
    "id": "price_Mailgun_Guide",
    "product": "prod_Mailgun_Guide",
    "unit_amount": 3500,
    "currency": "usd",
    "recurring_interval": "month",
    "active": "true",
    "nickname": "Mailgun Delivery - Guide Monthly"
  },
  {
    "id": "price_Cloudflare_Guide",
    "product": "prod_Cloudflare_Guide",
    "unit_amount": 2000,
    "currency": "usd",
    "recurring_interval": "month",
    "active": "true",
    "nickname": "Cloudflare Pro - Guide Monthly"
  },
  {
    "id": "price_Vimeo_Guide",
    "product": "prod_Vimeo_Guide",
    "unit_amount": 1200,
    "currency": "usd",
    "recurring_interval": "month",
    "active": "true",
    "nickname": "Vimeo Pro - Guide Monthly"
  },
  {
    "id": "price_Canva_Guide",
    "product": "prod_Canva_Guide",
    "unit_amount": 1299,
    "currency": "usd",
    "recurring_interval": "month",
    "active": "true",
    "nickname": "Canva Pro - Guide Monthly"
  }
]
