<?xml version="1.0" encoding="UTF-8"?>
<environmentalFeed xmlns="http://pereztextileconservation.com/schema/env"
                   studio="Perez Textile Conservation" exported="2026-02-14T17:30:00-05:00">
  <site id="PTC-JP" address="47 Pond Street, Jamaica Plain, MA 02130"/>
  <gateway id="GW-01" firmware="2.4.1" cloud="linked"/>
  <sensors>
    <sensor id="S-STOR-1" zone="Archival Storage" model="HOBO MX1101"/>
    <sensor id="S-TRMT-1" zone="Treatment Room" model="HOBO MX1101"/>
    <sensor id="S-CHMB-1" zone="Humidification Chamber" model="HOBO MX1101"/>
  </sensors>
  <readings>
    <reading sensor="S-STOR-1" time="2026-02-11T02:14:00-05:00">
      <temperatureC>19.4</temperatureC>
      <relativeHumidity>61</relativeHumidity>
      <status>ALERT</status>
      <note>RH above 55 percent setpoint</note>
    </reading>
    <reading sensor="S-STOR-1" time="2026-02-11T03:00:00-05:00">
      <temperatureC>19.3</temperatureC>
      <relativeHumidity>58</relativeHumidity>
      <status>WARN</status>
      <note>RH recovering</note>
    </reading>
    <reading sensor="S-STOR-1" time="2026-02-11T08:00:00-05:00">
      <temperatureC>19.5</temperatureC>
      <relativeHumidity>54</relativeHumidity>
      <status>OK</status>
    </reading>
    <reading sensor="S-TRMT-1" time="2026-02-11T08:00:00-05:00">
      <temperatureC>20.6</temperatureC>
      <relativeHumidity>51</relativeHumidity>
      <status>OK</status>
    </reading>
    <reading sensor="S-CHMB-1" time="2026-02-11T08:00:00-05:00">
      <temperatureC>21.0</temperatureC>
      <relativeHumidity>68</relativeHumidity>
      <status>OK</status>
      <note>Active humidification, panel 2024.1583.6</note>
    </reading>
    <reading sensor="S-STOR-1" time="2026-02-12T08:00:00-05:00">
      <temperatureC>19.5</temperatureC>
      <relativeHumidity>49</relativeHumidity>
      <status>OK</status>
    </reading>
    <reading sensor="S-TRMT-1" time="2026-02-12T14:00:00-05:00">
      <temperatureC>20.7</temperatureC>
      <relativeHumidity>52</relativeHumidity>
      <status>OK</status>
    </reading>
    <reading sensor="S-CHMB-1" time="2026-02-12T14:00:00-05:00">
      <temperatureC>20.9</temperatureC>
      <relativeHumidity>66</relativeHumidity>
      <status>OK</status>
      <note>Active humidification, panel 2024.1583.6</note>
    </reading>
  </readings>
</environmentalFeed>
