[
  {
    "caption": "Early run before class 🏃",
    "expiring_at": "2026-12-29T00:00:00+00:00",
    "id": "37951688601035563",
    "link": "https://syracuse.edu/stories-1",
    "media_type": "IMAGE",
    "media_url": "https://www.instagram.com/stories/37951688601035563.jpg",
    "poll_options": "standard",
    "poll_question": "Pizza run after the SGA meeting?",
    "timestamp": "2026-12-28T05:19:36+00:00",
    "user_id": "43535332979849936"
  },
  {
    "caption": "Pickup soccer on the quad ⚽",
    "expiring_at": "2026-12-28T05:10:01+00:00",
    "id": "59735444720854999",
    "link": "https://syracuse.edu/stories-2",
    "media_type": "IMAGE",
    "media_url": "https://www.instagram.com/stories/59735444720854999.jpg",
    "poll_options": "standard",
    "poll_question": "Pizza run after the SGA meeting?",
    "timestamp": "2026-12-28T06:35:29+00:00",
    "user_id": "43535332979849936"
  },
  {
    "caption": "Library study setup for finals 📚",
    "expiring_at": "2026-12-27T17:37:10+00:00",
    "id": "55757443476756644",
    "link": "https://syracuse.edu/stories-3",
    "media_type": "IMAGE",
    "media_url": "https://www.instagram.com/stories/55757443476756644.jpg",
    "poll_options": "standard",
    "poll_question": "Pizza run after the SGA meeting?",
    "timestamp": "2026-12-26T04:25:54+00:00",
    "user_id": "43535332979849936"
  },
  {
    "caption": "Slow Sunday. Meal prep + reading.",
    "expiring_at": "2026-12-27T14:17:37+00:00",
    "id": "10845848617484047",
    "link": "https://syracuse.edu/stories-4",
    "media_type": "IMAGE",
    "media_url": "https://www.instagram.com/stories/10845848617484047.jpg",
    "poll_options": "standard",
    "poll_question": "Pizza run after the SGA meeting?",
    "timestamp": "2026-12-25T18:23:57+00:00",
    "user_id": "43535332979849936"
  },
  {
    "caption": "SU game day at the Dome! 🍊",
    "expiring_at": "2026-12-25T07:29:07+00:00",
    "id": "40571812422561668",
    "link": "https://syracuse.edu/stories-5",
    "media_type": "IMAGE",
    "media_url": "https://www.instagram.com/stories/40571812422561668.jpg",
    "poll_options": "standard",
    "poll_question": "Pizza run after the SGA meeting?",
    "timestamp": "2026-12-28T20:50:45+00:00",
    "user_id": "43535332979849936"
  },
  {
    "caption": "Sunday slow-cooker experiment 🍲",
    "expiring_at": "2026-12-25T17:33:38+00:00",
    "id": "94059885597281845",
    "link": "https://syracuse.edu/stories-6",
    "media_type": "IMAGE",
    "media_url": "https://www.instagram.com/stories/94059885597281845.jpg",
    "poll_options": "standard",
    "poll_question": "Pizza run after the SGA meeting?",
    "timestamp": "2026-12-27T15:14:47+00:00",
    "user_id": "43535332979849936"
  },
  {
    "caption": "Early run before class 🏃",
    "expiring_at": "2026-10-07T00:00:00+00:00",
    "id": "37951688601035570",
    "link": "https://syracuse.edu/stories-1",
    "media_type": "IMAGE",
    "media_url": "https://www.instagram.com/stories/37951688601035563.jpg",
    "poll_options": "standard",
    "poll_question": "Pizza run after the SGA meeting?",
    "timestamp": "2026-10-07T05:19:36+00:00",
    "user_id": "43535332979849943"
  },
  {
    "caption": "Pickup soccer on the quad ⚽",
    "expiring_at": "2027-03-10T05:10:01+00:00",
    "id": "59735444720855007",
    "link": "https://syracuse.edu/stories-2",
    "media_type": "IMAGE",
    "media_url": "https://www.instagram.com/stories/59735444720854999.jpg",
    "poll_options": "standard",
    "poll_question": "Pizza run after the SGA meeting?",
    "timestamp": "2027-03-10T06:35:29+00:00",
    "user_id": "43535332979849944"
  },
  {
    "caption": "Library study setup for finals 📚",
    "expiring_at": "2026-11-15T17:37:10+00:00",
    "id": "55757443476756653",
    "link": "https://syracuse.edu/stories-3",
    "media_type": "IMAGE",
    "media_url": "https://www.instagram.com/stories/55757443476756644.jpg",
    "poll_options": "standard",
    "poll_question": "Pizza run after the SGA meeting?",
    "timestamp": "2026-11-15T04:25:54+00:00",
    "user_id": "43535332979849945"
  },
  {
    "caption": "Slow Sunday. Meal prep + reading.",
    "expiring_at": "2027-03-11T14:17:37+00:00",
    "id": "10845848617484057",
    "link": "https://syracuse.edu/stories-4",
    "media_type": "IMAGE",
    "media_url": "https://www.instagram.com/stories/10845848617484047.jpg",
    "poll_options": "standard",
    "poll_question": "Pizza run after the SGA meeting?",
    "timestamp": "2027-03-11T18:23:57+00:00",
    "user_id": "43535332979849946"
  },
  {
    "caption": "SU game day at the Dome! 🍊",
    "expiring_at": "2026-12-19T07:29:07+00:00",
    "id": "40571812422561679",
    "link": "https://syracuse.edu/stories-5",
    "media_type": "IMAGE",
    "media_url": "https://www.instagram.com/stories/40571812422561668.jpg",
    "poll_options": "standard",
    "poll_question": "Pizza run after the SGA meeting?",
    "timestamp": "2026-12-19T20:50:45+00:00",
    "user_id": "43535332979849947"
  },
  {
    "caption": "Sunday slow-cooker experiment 🍲",
    "expiring_at": "2027-01-30T17:33:38+00:00",
    "id": "94059885597281857",
    "link": "https://syracuse.edu/stories-6",
    "media_type": "IMAGE",
    "media_url": "https://www.instagram.com/stories/94059885597281845.jpg",
    "poll_options": "standard",
    "poll_question": "Pizza run after the SGA meeting?",
    "timestamp": "2027-01-30T15:14:47+00:00",
    "user_id": "43535332979849948"
  },
  {
    "caption": "Early run before class 🏃",
    "expiring_at": "2027-02-28T00:00:00+00:00",
    "id": "37951688601035576",
    "link": "https://syracuse.edu/stories-1",
    "media_type": "IMAGE",
    "media_url": "https://www.instagram.com/stories/37951688601035563.jpg",
    "poll_options": "standard",
    "poll_question": "Pizza run after the SGA meeting?",
    "timestamp": "2027-02-28T05:19:36+00:00",
    "user_id": "43535332979849949"
  },
  {
    "caption": "Pickup soccer on the quad ⚽",
    "expiring_at": "2027-01-06T05:10:01+00:00",
    "id": "59735444720855013",
    "link": "https://syracuse.edu/stories-2",
    "media_type": "IMAGE",
    "media_url": "https://www.instagram.com/stories/59735444720854999.jpg",
    "poll_options": "standard",
    "poll_question": "Pizza run after the SGA meeting?",
    "timestamp": "2027-01-06T06:35:29+00:00",
    "user_id": "43535332979849950"
  },
  {
    "caption": "Library study setup for finals 📚",
    "expiring_at": "2027-01-25T17:37:10+00:00",
    "id": "55757443476756659",
    "link": "https://syracuse.edu/stories-3",
    "media_type": "IMAGE",
    "media_url": "https://www.instagram.com/stories/55757443476756644.jpg",
    "poll_options": "standard",
    "poll_question": "Pizza run after the SGA meeting?",
    "timestamp": "2027-01-25T04:25:54+00:00",
    "user_id": "43535332979849951"
  },
  {
    "caption": "Slow Sunday. Meal prep + reading.",
    "expiring_at": "2026-11-04T14:17:37+00:00",
    "id": "10845848617484063",
    "link": "https://syracuse.edu/stories-4",
    "media_type": "IMAGE",
    "media_url": "https://www.instagram.com/stories/10845848617484047.jpg",
    "poll_options": "standard",
    "poll_question": "Pizza run after the SGA meeting?",
    "timestamp": "2026-11-04T18:23:57+00:00",
    "user_id": "43535332979849952"
  },
  {
    "caption": "SU game day at the Dome! 🍊",
    "expiring_at": "2026-11-26T07:29:07+00:00",
    "id": "40571812422561685",
    "link": "https://syracuse.edu/stories-5",
    "media_type": "IMAGE",
    "media_url": "https://www.instagram.com/stories/40571812422561668.jpg",
    "poll_options": "standard",
    "poll_question": "Pizza run after the SGA meeting?",
    "timestamp": "2026-11-26T20:50:45+00:00",
    "user_id": "43535332979849953"
  },
  {
    "caption": "Sunday slow-cooker experiment 🍲",
    "expiring_at": "2027-01-21T17:33:38+00:00",
    "id": "94059885597281863",
    "link": "https://syracuse.edu/stories-6",
    "media_type": "IMAGE",
    "media_url": "https://www.instagram.com/stories/94059885597281845.jpg",
    "poll_options": "standard",
    "poll_question": "Pizza run after the SGA meeting?",
    "timestamp": "2027-01-21T15:14:47+00:00",
    "user_id": "43535332979849954"
  },
  {
    "caption": "Early run before class 🏃",
    "expiring_at": "2027-01-20T00:00:00+00:00",
    "id": "37951688601035582",
    "link": "https://syracuse.edu/stories-1",
    "media_type": "IMAGE",
    "media_url": "https://www.instagram.com/stories/37951688601035563.jpg",
    "poll_options": "standard",
    "poll_question": "Pizza run after the SGA meeting?",
    "timestamp": "2027-01-20T05:19:36+00:00",
    "user_id": "43535332979849955"
  },
  {
    "caption": "Pickup soccer on the quad ⚽",
    "expiring_at": "2026-12-09T05:10:01+00:00",
    "id": "59735444720855019",
    "link": "https://syracuse.edu/stories-2",
    "media_type": "IMAGE",
    "media_url": "https://www.instagram.com/stories/59735444720854999.jpg",
    "poll_options": "standard",
    "poll_question": "Pizza run after the SGA meeting?",
    "timestamp": "2026-12-09T06:35:29+00:00",
    "user_id": "43535332979849956"
  }
]
