[
  {
    "id": "price_Starter_M",
    "product": "prod_Starter",
    "unit_amount": "500",
    "currency": "usd",
    "recurring_interval": "month",
    "active": "true",
    "nickname": "Monthly $5"
  },
  {
    "id": "price_Pro_M",
    "product": "prod_Pro",
    "unit_amount": "5000",
    "currency": "usd",
    "recurring_interval": "year",
    "active": "true",
    "nickname": "Annual $50"
  },
  {
    "id": "price_Pro_Y",
    "product": "prod_Pro",
    "unit_amount": "5000",
    "currency": "usd",
    "recurring_interval": "year",
    "active": "true",
    "nickname": "Annual $50 alt"
  },
  {
    "id": "price_Ent_M",
    "product": "prod_Enterprise",
    "unit_amount": "12000",
    "currency": "usd",
    "recurring_interval": "year",
    "active": "true",
    "nickname": "Founding Member $120"
  },
  {
    "id": "price_POS",
    "product": "prod_POS",
    "unit_amount": "1500",
    "currency": "usd",
    "recurring_interval": "month",
    "active": "true",
    "nickname": "Essay Zine One-time"
  },
  {
    "id": "price_Starter_M-7",
    "product": "prod_Starter",
    "unit_amount": "500",
    "currency": "usd",
    "recurring_interval": "month",
    "active": "true",
    "nickname": "Monthly $5"
  },
  {
    "id": "price_Pro_M-8",
    "product": "prod_Pro",
    "unit_amount": "5000",
    "currency": "usd",
    "recurring_interval": "year",
    "active": "true",
    "nickname": "Annual $50"
  },
  {
    "id": "price_Pro_Y-9",
    "product": "prod_Pro",
    "unit_amount": "5000",
    "currency": "usd",
    "recurring_interval": "year",
    "active": "true",
    "nickname": "Annual $50 alt"
  },
  {
    "id": "price_Ent_M-10",
    "product": "prod_Enterprise",
    "unit_amount": "12000",
    "currency": "usd",
    "recurring_interval": "year",
    "active": "true",
    "nickname": "Founding Member $120"
  },
  {
    "id": "price_POS-11",
    "product": "prod_POS",
    "unit_amount": "1500",
    "currency": "usd",
    "recurring_interval": "month",
    "active": "true",
    "nickname": "Essay Zine One-time"
  },
  {
    "id": "price_Starter_M-12",
    "product": "prod_Starter",
    "unit_amount": "500",
    "currency": "usd",
    "recurring_interval": "month",
    "active": "true",
    "nickname": "Monthly $5"
  },
  {
    "id": "price_Pro_M-13",
    "product": "prod_Pro",
    "unit_amount": "5000",
    "currency": "usd",
    "recurring_interval": "year",
    "active": "true",
    "nickname": "Annual $50"
  },
  {
    "id": "price_Pro_Y-14",
    "product": "prod_Pro",
    "unit_amount": "5000",
    "currency": "usd",
    "recurring_interval": "year",
    "active": "true",
    "nickname": "Annual $50 alt"
  },
  {
    "id": "price_Ent_M-15",
    "product": "prod_Enterprise",
    "unit_amount": "12000",
    "currency": "usd",
    "recurring_interval": "year",
    "active": "true",
    "nickname": "Founding Member $120"
  },
  {
    "id": "price_POS-16",
    "product": "prod_POS",
    "unit_amount": "1500",
    "currency": "usd",
    "recurring_interval": "month",
    "active": "true",
    "nickname": "Essay Zine One-time"
  },
  {
    "id": "price_Starter_M-17",
    "product": "prod_Starter",
    "unit_amount": "500",
    "currency": "usd",
    "recurring_interval": "month",
    "active": "true",
    "nickname": "Monthly $5"
  },
  {
    "id": "price_Pro_M-18",
    "product": "prod_Pro",
    "unit_amount": "5000",
    "currency": "usd",
    "recurring_interval": "year",
    "active": "true",
    "nickname": "Annual $50"
  },
  {
    "id": "price_Pro_Y-19",
    "product": "prod_Pro",
    "unit_amount": "5000",
    "currency": "usd",
    "recurring_interval": "year",
    "active": "true",
    "nickname": "Annual $50 alt"
  },
  {
    "id": "price_Ent_M-20",
    "product": "prod_Enterprise",
    "unit_amount": "12000",
    "currency": "usd",
    "recurring_interval": "year",
    "active": "true",
    "nickname": "Founding Member $120"
  },
  {
    "id": "price_POS-21",
    "product": "prod_POS",
    "unit_amount": "1500",
    "currency": "usd",
    "recurring_interval": "month",
    "active": "true",
    "nickname": "Essay Zine One-time"
  }
]