<?xml version="1.0" encoding="UTF-8"?>
<library owner="Jennifer Williams" location="Providence, RI" exported="2026-10-19">
  <description>Working playlists, sorted by what they are for. Ambient to draft, something precise and sad to cut.</description>

  <playlist name="Underpainting" mode="Drafting" trackCount="42" lastPlayed="2026-10-18">
    <mood>Loose, open, no words I can parse</mood>
    <whenUsed>Early morning before an opening shift</whenUsed>
    <tracks>
      <track title="Should Have Known Better" artist="Sufjan Stevens" minutes="5.1"/>
      <track title="Death with Dignity" artist="Sufjan Stevens" minutes="4.0"/>
      <track title="Holland" artist="Sufjan Stevens" minutes="3.4"/>
      <track title="An Ocean of Static" artist="Hammock" minutes="6.2"/>
    </tracks>
  </playlist>

  <playlist name="Low Tide" mode="Drafting" trackCount="31" lastPlayed="2026-10-16">
    <mood>Warm static, room tone</mood>
    <whenUsed>Afternoons at the desk</whenUsed>
    <tracks>
      <track title="Paul" artist="Big Thief" minutes="4.3"/>
      <track title="Mary" artist="Big Thief" minutes="4.9"/>
      <track title="Cattails" artist="Big Thief" minutes="4.5"/>
      <track title="Two Hands" artist="Big Thief" minutes="3.9"/>
    </tracks>
  </playlist>

  <playlist name="Ambient Room" mode="Drafting" trackCount="18" lastPlayed="2026-10-12">
    <mood>No melody, just weather</mood>
    <whenUsed>When a poem will not start</whenUsed>
    <tracks>
      <track title="An Ending, Ascent" artist="Brian Eno" minutes="4.4"/>
      <track title="The Big Ship" artist="Brian Eno" minutes="3.0"/>
      <track title="By This River" artist="Brian Eno" minutes="3.0"/>
    </tracks>
  </playlist>

  <playlist name="Cut It Down" mode="Editing" trackCount="27" lastPlayed="2026-10-17">
    <mood>Precise, sad, exact</mood>
    <whenUsed>Line edits, cutting the fat</whenUsed>
    <tracks>
      <track title="Funeral" artist="Phoebe Bridgers" minutes="4.5"/>
      <track title="Scott Street" artist="Phoebe Bridgers" minutes="5.0"/>
      <track title="Moon Song" artist="Phoebe Bridgers" minutes="4.2"/>
    </tracks>
  </playlist>

  <playlist name="String Section" mode="Editing" trackCount="22" lastPlayed="2026-10-14">
    <mood>Classical, structural</mood>
    <whenUsed>Final read before sending</whenUsed>
    <tracks>
      <track title="On the Nature of Daylight" artist="Max Richter" minutes="6.1"/>
      <track title="Vladimir's Blues" artist="Max Richter" minutes="1.7"/>
      <track title="Spring 1" artist="Max Richter" minutes="3.3"/>
    </tracks>
  </playlist>

  <playlist name="Open Mic Warmup" mode="Performing" trackCount="15" lastPlayed="2026-10-16">
    <mood>Nerve and adrenaline</mood>
    <whenUsed>The bus ride to a reading</whenUsed>
    <tracks>
      <track title="Nobody" artist="Mitski" minutes="3.4"/>
      <track title="Your Best American Girl" artist="Mitski" minutes="3.5"/>
      <track title="First Love, Late Spring" artist="Mitski" minutes="3.6"/>
    </tracks>
  </playlist>

  <playlist name="Closing Shift" mode="Other" trackCount="20" lastPlayed="2026-10-15">
    <mood>Wind down, mop water</mood>
    <whenUsed>The last hour at Alchemy</whenUsed>
    <tracks>
      <track title="Maria Also" artist="Khruangbin" minutes="4.6"/>
      <track title="August 10" artist="Khruangbin" minutes="3.6"/>
      <track title="So We Won't Forget" artist="Khruangbin" minutes="4.0"/>
    </tracks>
  </playlist>
</library>
