[
  {
    "asset_id": "93bc2999-dab1-8a96-4ad8-7b8bf07dfce8",
    "avg_entry_price": "196.10",
    "cost_basis": "8628.40",
    "current_price": "237.10",
    "market_value": "10432.40",
    "qty": "44",
    "side": "long",
    "symbol": "AAPL",
    "unrealized_pl": "1804.00"
  },
  {
    "asset_id": "cd4246b4-4849-cda6-41f9-8f3e12f0f7ba",
    "avg_entry_price": "389.60",
    "cost_basis": "16363.20",
    "current_price": "416.16",
    "market_value": "17478.72",
    "qty": "42",
    "side": "long",
    "symbol": "MSFT",
    "unrealized_pl": "1115.52"
  },
  {
    "asset_id": "6afeedc5-31af-ca94-410c-a8b8d863fde9",
    "avg_entry_price": "162.61",
    "cost_basis": "5203.52",
    "current_price": "174.03",
    "market_value": "5568.96",
    "qty": "32",
    "side": "long",
    "symbol": "GOOGL",
    "unrealized_pl": "365.44"
  },
  {
    "asset_id": "f93cb52c-8dba-d299-4346-908e0c731dee",
    "avg_entry_price": "185.04",
    "cost_basis": "8326.80",
    "current_price": "196.25",
    "market_value": "8831.25",
    "qty": "45",
    "side": "long",
    "symbol": "AMZN",
    "unrealized_pl": "504.45"
  },
  {
    "asset_id": "4dd2e491-c5ef-7cb0-4185-1f0b36e37078",
    "avg_entry_price": "131.80",
    "cost_basis": "6458.20",
    "current_price": "141.65",
    "market_value": "6940.85",
    "qty": "49",
    "side": "long",
    "symbol": "NVDA",
    "unrealized_pl": "482.65"
  },
  {
    "asset_id": "5894eae4-5549-3c91-46a7-6b53eea9d3d3",
    "avg_entry_price": "501.17",
    "cost_basis": "25559.67",
    "current_price": "575.11",
    "market_value": "29330.61",
    "qty": "51",
    "side": "long",
    "symbol": "META",
    "unrealized_pl": "3770.94"
  },
  {
    "asset_id": "1fe78636-af70-9ab4-4568-7f608675e36f",
    "avg_entry_price": "532.15",
    "cost_basis": "5321.50",
    "current_price": "548.30",
    "market_value": "5483.00",
    "qty": "10",
    "side": "long",
    "symbol": "VOO",
    "unrealized_pl": "161.50"
  },
  {
    "asset_id": "2298beb9-014e-3589-44ff-6053a429945d",
    "avg_entry_price": "286.40",
    "cost_basis": "4296.00",
    "current_price": "294.85",
    "market_value": "4422.75",
    "qty": "15",
    "side": "long",
    "symbol": "VTI",
    "unrealized_pl": "126.75"
  },
  {
    "asset_id": "8d3f1c47-2a9b-4e60-91c5-7b0e2f6a4d18",
    "avg_entry_price": "588.20",
    "cost_basis": "2941.00",
    "current_price": "601.40",
    "market_value": "3007.00",
    "qty": "5",
    "side": "long",
    "symbol": "SPY",
    "unrealized_pl": "66.00"
  },
  {
    "asset_id": "49c05f15-69aa-0242-6003-07c65429cd41",
    "avg_entry_price": "364.36",
    "cost_basis": "10610.01",
    "current_price": "282.80",
    "market_value": "25660.08",
    "qty": "11",
    "side": "long",
    "symbol": "AAPL",
    "unrealized_pl": "2378.77"
  },
  {
    "asset_id": "26dd07eb-e436-9b0d-46fa-3a8e194a0320",
    "avg_entry_price": "586.55",
    "cost_basis": "8704.63",
    "current_price": "403.59",
    "market_value": "9237.19",
    "qty": "23",
    "side": "long",
    "symbol": "MSFT",
    "unrealized_pl": "2251.32"
  },
  {
    "asset_id": "5ff51825-47cb-6a6d-66cd-5742b3e70a04",
    "avg_entry_price": "171.21",
    "cost_basis": "9622.33",
    "current_price": "546.47",
    "market_value": "3063.90",
    "qty": "5",
    "side": "long",
    "symbol": "GOOGL",
    "unrealized_pl": "2956.07"
  },
  {
    "asset_id": "e4825e8d-cf73-3118-d72d-e1462c6fa610",
    "avg_entry_price": "529.98",
    "cost_basis": "23620.00",
    "current_price": "507.95",
    "market_value": "26490.63",
    "qty": "10",
    "side": "long",
    "symbol": "AMZN",
    "unrealized_pl": "2868.92"
  },
  {
    "asset_id": "7b44c749-1959-d5fd-5922-45a39234d8f4",
    "avg_entry_price": "237.22",
    "cost_basis": "10946.62",
    "current_price": "360.04",
    "market_value": "17358.65",
    "qty": "23",
    "side": "long",
    "symbol": "NVDA",
    "unrealized_pl": "2588.14"
  },
  {
    "asset_id": "2a0ca48c-cd60-2028-acb8-bfddc42440b4",
    "avg_entry_price": "148.82",
    "cost_basis": "18439.21",
    "current_price": "367.78",
    "market_value": "5127.61",
    "qty": "48",
    "side": "long",
    "symbol": "META",
    "unrealized_pl": "569.57"
  },
  {
    "asset_id": "308e1f7e-3308-9e9c-8b82-b794767b8b48",
    "avg_entry_price": "356.61",
    "cost_basis": "13675.54",
    "current_price": "339.03",
    "market_value": "12519.92",
    "qty": "32",
    "side": "long",
    "symbol": "VOO",
    "unrealized_pl": "1415.68"
  },
  {
    "asset_id": "121c7b53-4f96-48be-3051-14807fe4565d",
    "avg_entry_price": "505.44",
    "cost_basis": "19969.08",
    "current_price": "494.99",
    "market_value": "19940.60",
    "qty": "32",
    "side": "long",
    "symbol": "VTI",
    "unrealized_pl": "1791.69"
  },
  {
    "asset_id": "775987ad-eee0-3cb9-84e8-59ff672631f4",
    "avg_entry_price": "582.74",
    "cost_basis": "18722.27",
    "current_price": "269.03",
    "market_value": "10531.79",
    "qty": "19",
    "side": "long",
    "symbol": "SPY",
    "unrealized_pl": "1868.45"
  },
  {
    "asset_id": "ad4a5d8b-5277-9e48-9b69-5c96c1ac85f6",
    "avg_entry_price": "168.61",
    "cost_basis": "19861.49",
    "current_price": "344.48",
    "market_value": "12744.00",
    "qty": "11",
    "side": "long",
    "symbol": "AAPL",
    "unrealized_pl": "2530.93"
  },
  {
    "asset_id": "031562c0-35f5-5a09-f7e9-5654ddcad0a9",
    "avg_entry_price": "456.65",
    "cost_basis": "7744.06",
    "current_price": "159.98",
    "market_value": "25091.67",
    "qty": "33",
    "side": "long",
    "symbol": "MSFT",
    "unrealized_pl": "3710.90"
  }
]
