<?xml version="1.0" encoding="UTF-8"?>
<library owner="Brian Patterson" exported="2026-01-19">
  <profile>
    <displayName>brian.p</displayName>
    <plan>Student</plan>
    <listening>
      <mode name="study" note="lo-fi and ambient for deep work"/>
      <mode name="rotation" note="R and B, hip hop, and alternative rock"/>
    </listening>
  </profile>

  <playlist id="PL01" name="Library Hours" mood="focus" trackCount="10" minutes="35">
    <description>Quiet instrumentals for late stacks and long carrels.</description>
    <track order="1" title="Late Stacks" artist="Maple Court" length="3:12"/>
    <track order="2" title="Quiet Quad" artist="Ren Holloway" length="2:58"/>
    <track order="3" title="Rain on Marshall" artist="Lowtide" length="4:05"/>
    <track order="4" title="Margin Notes" artist="Cassette Hours" length="3:30"/>
    <track order="5" title="Second Floor Carrel" artist="Maple Court" length="3:44"/>
    <track order="6" title="Slow Coffee" artist="Ren Holloway" length="2:41"/>
    <track order="7" title="Index Cards" artist="Paper Lanes" length="3:18"/>
    <track order="8" title="Footnotes" artist="Lowtide" length="4:22"/>
    <track order="9" title="Due at Midnight" artist="Cassette Hours" length="3:05"/>
    <track order="10" title="Closing Time Library" artist="Paper Lanes" length="3:51"/>
  </playlist>

  <playlist id="PL02" name="Morning Run" mood="energy" trackCount="6" minutes="22">
    <description>Steady tempo for an easy two to three miles around campus.</description>
    <track order="1" title="Westcott Sunrise" artist="North Side" length="3:36"/>
    <track order="2" title="Creekwalk" artist="Ada Vaughn" length="3:48"/>
    <track order="3" title="Thornden" artist="The Mile Markers" length="4:01"/>
    <track order="4" title="Easy Pace" artist="North Side" length="3:22"/>
    <track order="5" title="Comstock Hill" artist="Ada Vaughn" length="3:55"/>
    <track order="6" title="Cool Down" artist="The Mile Markers" length="3:10"/>
  </playlist>

  <playlist id="PL03" name="Kitchen Sunday" mood="warm" trackCount="6" minutes="24">
    <description>For the slow cooker afternoons and a beef stew that is almost right.</description>
    <track order="1" title="Low and Slow" artist="Marrow and Thyme" length="4:12"/>
    <track order="2" title="Brown the Beef" artist="Cast Iron" length="3:40"/>
    <track order="3" title="Bay Leaf" artist="Marrow and Thyme" length="3:58"/>
    <track order="4" title="Deglaze" artist="Cast Iron" length="4:20"/>
    <track order="5" title="Two Hours In" artist="Greenhouse Trio" length="3:48"/>
    <track order="6" title="Taste Test" artist="Greenhouse Trio" length="4:02"/>
  </playlist>

  <playlist id="PL04" name="Finals Cold Brew" mood="lock in" trackCount="5" minutes="20">
    <description>The escalation playlist, kept for the week the latte becomes cold brew.</description>
    <track order="1" title="Last Push" artist="Cassette Hours" length="3:58"/>
    <track order="2" title="One More Chapter" artist="Lowtide" length="4:10"/>
    <track order="3" title="Blue Light" artist="Maple Court" length="3:46"/>
    <track order="4" title="Eight More Pages" artist="Paper Lanes" length="4:05"/>
    <track order="5" title="Submit" artist="Ren Holloway" length="3:32"/>
  </playlist>
</library>
