<?xml version="1.0" encoding="UTF-8"?>
<household_budget_tracker family="Morales" address="4217 W San Rafael Street, Tampa, FL 33629" tax_year="2026">

  <income>
    <earner name="Brittany Morales" type="self_employment">
      <annual_target>120000</annual_target>
      <annual_base_estimate>95000</annual_base_estimate>
      <ytd_commission as_of="2026-10-10">36690</ytd_commission>
      <commission_structure>80 percent of gross, minus 500 per month desk fee to SunCoast Realty Group</commission_structure>
      <note>Variable. Commission driven by closings. Q4 pipeline strong: Westchase at 525K and Channelside at 285K both near closing.</note>
    </earner>
    <earner name="Eric Morales" type="w2_employee">
      <annual_salary>78000</annual_salary>
      <average_bonus>8000</average_bonus>
      <total_expected>86000</total_expected>
      <employer>West Marine - marine supply sales</employer>
    </earner>
    <combined_household_annual>206000</combined_household_annual>
  </income>

  <fixed_expenses label="Monthly recurring, consistent every month">
    <expense category="Housing">
      <line item="Mortgage - Truist, account 0042-887611" monthly="2600" annual="31200" note="3.9% fixed, 24 years remaining"/>
    </expense>
    <expense category="Professional">
      <line item="SunCoast Realty desk fee" monthly="500" annual="6000"/>
      <line item="Marketing budget (ads, print, Mailchimp, Canva)" monthly="1200" annual="14400"/>
    </expense>
    <expense category="Insurance">
      <line item="Auto and home combined" monthly="420" annual="5040"/>
    </expense>
    <expense category="Family">
      <line item="Megan volleyball club dues and travel" monthly="600" annual="7200"/>
      <line item="Kids activities (Diego robotics, lessons)" monthly="300" annual="3600"/>
      <line item="Support to Carmen Herrera" monthly="400" annual="4800"/>
    </expense>
    <expense category="Pool and Lawn">
      <line item="Aqua Blue pool service" monthly="180" annual="2160"/>
      <line item="Hernandez landscaping" monthly="150" annual="1800"/>
    </expense>
    <expense category="Savings and Investment">
      <line item="Capital One savings transfer" monthly="500" annual="6000"/>
      <line item="Megan 529 contribution (Florida plan)" monthly="200" annual="2400" balance_oct="18000"/>
      <line item="Diego 529 contribution (Florida plan)" monthly="200" annual="2400" balance_oct="12000"/>
    </expense>
    <expense category="Streaming and Entertainment">
      <line item="Netflix and Hulu" monthly="28" annual="336"/>
      <line item="Spotify" monthly="10" annual="120"/>
    </expense>
    <expense category="Wellness">
      <line item="LA Fitness South Tampa" monthly="45" annual="540"/>
    </expense>
  </fixed_expenses>

  <variable_expenses label="Monthly variable, based on spend category">
    <month label="2026-01">
      <category name="Groceries" budgeted="950" actual="978"/>
      <category name="Dining out" budgeted="350" actual="302"/>
      <category name="Gas and mileage" budgeted="350" actual="388"/>
      <category name="Utilities (TECO and water)" budgeted="320" actual="298"/>
      <category name="Clothing" budgeted="250" actual="189"/>
    </month>
    <month label="2026-02">
      <category name="Groceries" budgeted="950" actual="1012"/>
      <category name="Dining out" budgeted="350" actual="318"/>
      <category name="Gas and mileage" budgeted="350" actual="366"/>
      <category name="Utilities (TECO and water)" budgeted="320" actual="341"/>
      <category name="Clothing" budgeted="250" actual="205"/>
    </month>
    <month label="2026-10">
      <category name="Groceries" budgeted="950" actual="1044" note="Costco run plus open house refreshments"/>
      <category name="Dining out" budgeted="350" actual="412" note="Anniversary dinner at Columbia Restaurant included"/>
      <category name="Gas and mileage" budgeted="350" actual="401" note="Westchase open house and Clearwater volleyball"/>
      <category name="Utilities (TECO and water)" budgeted="320" actual="309"/>
      <category name="Clothing" budgeted="250" actual="231" note="Gel manicure Luxe Nail Spa 55 per visit, two visits"/>
    </month>
  </variable_expenses>

  <upcoming_large_expenses>
    <expense description="Pool pump repair or replacement" estimate_low="450" estimate_high="1200" timing="Q4 2026 or Q1 2027" priority="High"/>
    <expense description="Home office desk chair replacement" estimate="400" timing="Q4 2026" priority="Medium"/>
    <expense description="Roof replacement (12-year-old roof)" estimate_low="18000" estimate_high="22000" timing="2028-2031 estimated" priority="Plan ahead"/>
    <expense description="Florida Realtors Convention - Orlando" confirmed="279" hotel="TBD" timing="2026-12-09" priority="Booked"/>
    <expense description="Megan quinceañera" estimate_low="12000" estimate_high="15000" timing="2026-11-21" priority="Active planning - Carmen contributing to food"/>
  </upcoming_large_expenses>

  <emergency_fund>
    <institution>Capital One 360</institution>
    <apy>4.1</apy>
    <balance>32000</balance>
    <months_covered>4</months_covered>
    <note>Target is six months. Current four-month cushion is adequate but worth growing when commission income allows.</note>
  </emergency_fund>

  <home_equity>
    <property>4217 W San Rafael Street, Tampa, FL 33629</property>
    <estimated_value>561000</estimated_value>
    <mortgage_balance>381442</mortgage_balance>
    <estimated_equity>179558</estimated_equity>
    <heloc_potential>Approximately 143000 at 80 percent LTV minus mortgage balance</heloc_potential>
    <heloc_consideration>Possible use: down payment on 200,000 dollar investment condo in Channelside. Modeling underway with Hernandez and Associates.</heloc_consideration>
  </home_equity>

  <quarterly_tax_estimates>
    <cpa>Hernandez and Associates, (813) 555-0279, tax@hernandezcpa.com</cpa>
    <payment period="Q4-2025" amount="4150" due="2026-01-15" status="submitted"/>
    <payment period="Q1-2026" amount="5200" due="2026-04-15" status="paid" note="Raised per CPA guidance if 120K income achieved"/>
    <payment period="Q2-2026" amount="5200" due="2026-06-15" status="paid"/>
    <payment period="Q3-2026" amount="5200" due="2026-09-15" status="paid"/>
    <payment period="Q4-2026" amount="5200" due="2027-01-15" status="pending" note="Confirm with Hernandez before deadline"/>
  </quarterly_tax_estimates>

</household_budget_tracker>
